PyCondorRaven/__init__.py
PyCondorRaven/agents.py
PyCondorRaven/compare_value_against_returns.py
PyCondorRaven/database.py
PyCondorRaven/dynamo.py
PyCondorRaven/features_selection.py
PyCondorRaven/gcp.py
PyCondorRaven/hyperparam_optim.py
PyCondorRaven/llms.py
PyCondorRaven/main.py
PyCondorRaven/models.py
PyCondorRaven/preprocess_dataset.py
PyCondorRaven/raven.py
PyCondorRaven/reinforcement.py
PyCondorRaven/representation.py
PyCondorRaven/select_features_manually.py
PyCondorRaven/series_predictor.py
PyCondorRaven/series_predictor_lt.py
PyCondorRaven/simulation.py
PyCondorRaven/test_algorithms.py
PyCondorRaven/test_time.py
PyCondorRaven/tools.py
PyCondorRaven/utils.py
pycondorraven-1.0.39.dist-info/licenses/LICENSE.md
pycondorraven-1.0.39.dist-info/METADATA
pycondorraven-1.0.39.dist-info/WHEEL
pycondorraven-1.0.39.dist-info/top_level.txt
pycondorraven-1.0.39.dist-info/RECORD
