Metadata-Version: 2.4
Name: PyCondorRaven
Version: 1.0.39
Summary: Investment analytics and machine learning tools
Home-page: https://s3pip-library.s3.amazonaws.com
Author: Daniel Velasquez
Author-email: daniel.velasquez@sura-im.com
Classifier: Programming Language :: Python :: 3
Classifier: License :: OSI Approved :: MIT License
Classifier: Operating System :: OS Independent
Requires-Python: >=3.6
License-File: LICENSE.md
Dynamic: author
Dynamic: author-email
Dynamic: classifier
Dynamic: home-page
Dynamic: license-file
Dynamic: requires-python
Dynamic: summary
